dmc_floss_gimp_color_palette_generator/__init__.py
dmc_floss_gimp_color_palette_generator/__version__.py
dmc_floss_gimp_color_palette_generator/generator.py
dmc_floss_gimp_color_palette_generator/gpl.py
dmc_floss_gimp_color_palette_generator-1.0.0.dist-info/LICENSE
dmc_floss_gimp_color_palette_generator-1.0.0.dist-info/METADATA
dmc_floss_gimp_color_palette_generator-1.0.0.dist-info/WHEEL
dmc_floss_gimp_color_palette_generator-1.0.0.dist-info/entry_points.txt
dmc_floss_gimp_color_palette_generator-1.0.0.dist-info/top_level.txt
dmc_floss_gimp_color_palette_generator-1.0.0.dist-info/RECORD
