Metadata-Version: 2.1
Name: dmc-floss-gimp-color-palette-generator
Version: 1.0.0
Summary: Generates a GIMP palette with DMC floss colors from data scraped from the web.
Home-page: https://github.com/ksletmoe/dmc_floss_gimp_color_palette_generator
Author: Kyle Sletmoe
Author-email: kyle.sletmoe@gmail.com
License: BSD
Platform: UNKNOWN
Classifier: License :: OSI Approved :: BSD License
Classifier: Programming Language :: Python
Classifier: Programming Language :: Python :: 3
Classifier: Programming Language :: Python :: 3.7
Classifier: Programming Language :: Python :: 3.8
Classifier: Programming Language :: Python :: 3.9
Classifier: Programming Language :: Python :: Implementation :: CPython
Requires-Python: >=3.7.0
License-File: LICENSE
Requires-Dist: requests
Requires-Dist: beautifulsoup4
Provides-Extra: distribution
Requires-Dist: twine ; extra == 'distribution'
